mlpc/__init__.py
mlpc/metadata.py
mlpc/configuration/__init__.py
mlpc/entity/__init__.py
mlpc/entity/base_entities.py
mlpc/entity/code.py
mlpc/entity/data.py
mlpc/entity/measurement.py
mlpc/entity/model.py
mlpc/entity/parameters.py
mlpc/entity/plot.py
mlpc/runs/__init__.py
mlpc/runs/base_run.py
mlpc/runs/training_run.py
mlpc/storage/__init__.py
mlpc/storage/folderstorage.py
mlpc/utils/__init__.py
mlpc/utils/checksum.py
mlpc/utils/json_object_serializer.py
mlpc/utils/log.py
mlpc-0.0.27.dist-info/LICENSE
mlpc-0.0.27.dist-info/METADATA
mlpc-0.0.27.dist-info/WHEEL
mlpc-0.0.27.dist-info/top_level.txt
mlpc-0.0.27.dist-info/RECORD
