Metadata-Version: 2.1
Name: mlpc
Version: 0.0.27
Summary: A python beginners attempt at a micro framework for ML projects.
Home-page: https://tbd
Author: Snorre Visnes
Author-email: snorre.visnes+mlpc@gmail.com
License: UNKNOWN
Platform: UNKNOWN
Classifier: Programming Language :: Python :: 3
Classifier: License :: OSI Approved :: MIT License
Classifier: Operating System :: OS Independent
